{"inkVersion":20,"root":[["^How are you,sir?","\n",{"->":"My_choice"},["done",{"#f":5,"#n":"g-0"}],null],"done",{"My_choice":[["ev","str","^Well","/str","/ev",{"*":".^.c-0","flg":4},"ev","str","^bad","/str","/ev",{"*":".^.c-1","flg":4},"ev","str","^what?","/str","/ev",{"*":".^.c-2","flg":4},{"c-0":["^ ",{"->":"Good"},"\n",{"#f":5}],"c-1":["^ ",{"->":"bad"},"\n",{"#f":5}],"c-2":["^ ",{"->":"repeat"},"\n",{"#f":5}]}],{"#f":1}],"Good":["^I am doing well","\n","end",{"#f":1}],"bad":["^I am sad today","\n","end",{"#f":1}],"repeat":["^How are you?","\n",{"->":"My_choice"},{"#f":1}],"#f":1}],"listDefs":{}}